cdp_ninja/__init__.py
cdp_ninja/_version.py
cdp_ninja/config.py
cdp_ninja/constants.py
cdp_ninja/server.py
cdp_ninja/core/__init__.py
cdp_ninja/core/cdp_client.py
cdp_ninja/core/cdp_pool.py
cdp_ninja/core/domain_manager.py
cdp_ninja/core/event_manager.py
cdp_ninja/deployment/__init__.py
cdp_ninja/deployment/cli.py
cdp_ninja/deployment/installers.py
cdp_ninja/deployment/platforms.py
cdp_ninja/deployment/ssh_utils.py
cdp_ninja/deployment/verification.py
cdp_ninja/dom/__init__.py
cdp_ninja/dom/coordinates.py
cdp_ninja/examples/basic_usage.py
cdp_ninja/examples/debug_nextjs.py
cdp_ninja/interaction/__init__.py
cdp_ninja/interaction/coordinates.py
cdp_ninja/interaction/mouse.py
cdp_ninja/routes/__init__.py
cdp_ninja/routes/accessibility.py
cdp_ninja/routes/browser.py
cdp_ninja/routes/debugging.py
cdp_ninja/routes/dom.py
cdp_ninja/routes/dom_advanced.py
cdp_ninja/routes/error_handling.py
cdp_ninja/routes/js_debugging.py
cdp_ninja/routes/navigation.py
cdp_ninja/routes/network_intelligence.py
cdp_ninja/routes/performance.py
cdp_ninja/routes/route_utils.py
cdp_ninja/routes/security.py
cdp_ninja/routes/stress_testing.py
cdp_ninja/routes/stress_testing_advanced.py
cdp_ninja/routes/system.py
cdp_ninja/setup/install.py
cdp_ninja/setup/setup_unix.sh
cdp_ninja/setup/setup_windows.ps1
cdp_ninja/templates/__init__.py
cdp_ninja/templates/concurrency_js.py
cdp_ninja/templates/javascript.py
cdp_ninja/templates/stress_testing_js.py
cdp_ninja/utils/__init__.py
cdp_ninja/utils/error_handling.py
cdp_ninja/utils/error_reporter.py
cdp_ninja-2.0.8.data/data/agents/cdp-ninja-cloud-hiding.md
cdp_ninja-2.0.8.data/data/agents/cdp-ninja-divine-immovable.md
cdp_ninja-2.0.8.data/data/agents/cdp-ninja-hidden-door.md
cdp_ninja-2.0.8.data/data/agents/cdp-ninja-high-tree.md
cdp_ninja-2.0.8.data/data/agents/cdp-ninja-jewel-heart.md
cdp_ninja-2.0.8.data/data/agents/cdp-ninja-jewel-tiger.md
cdp_ninja-2.0.8.data/data/agents/cdp-ninja-nine-demons.md
cdp_ninja-2.0.8.data/data/agents/cdp-ninja-righteous.md
cdp_ninja-2.0.8.dist-info/LICENSE
cdp_ninja-2.0.8.dist-info/METADATA
cdp_ninja-2.0.8.dist-info/WHEEL
cdp_ninja-2.0.8.dist-info/entry_points.txt
cdp_ninja-2.0.8.dist-info/top_level.txt
cdp_ninja-2.0.8.dist-info/RECORD
