Metadata-Version: 2.1
Name: cdp-ninja
Version: 2.0.8
Summary: 🥷 Lightweight Chrome DevTools Protocol bridge for browser debugging and security testing
Home-page: https://github.com/travofoz/cdp-ninja
Author: CDP Ninja Contributors
Author-email: CDP Ninja Contributors <dev@example.com>
License: MIT
Project-URL: Homepage, https://github.com/travofoz/cdp-ninja
Project-URL: Repository, https://github.com/travofoz/cdp-ninja
Project-URL: Issues, https://github.com/travofoz/cdp-ninja/issues
Project-URL: Documentation, https://github.com/travofoz/cdp-ninja/wiki
Keywords: chrome,devtools,debugging,browser,automation,cdp,testing,performance,network,console,security,fuzzing,vulnerability,penetration-testing
Classifier: Development Status :: 4 - Beta
Classifier: Intended Audience :: Developers
Classifier: Intended Audience :: Information Technology
Classifier: Topic :: Software Development :: Debuggers
Classifier: Topic :: Software Development :: Testing
Classifier: Topic :: Internet :: WWW/HTTP :: Browsers
Classifier: Topic :: Security
Classifier: Topic :: System :: Networking :: Monitoring
Classifier: License :: OSI Approved :: MIT License
Classifier: Operating System :: OS Independent
Classifier: Programming Language :: Python :: 3
Classifier: Programming Language :: Python :: 3.8
Classifier: Programming Language :: Python :: 3.9
Classifier: Programming Language :: Python :: 3.10
Classifier: Programming Language :: Python :: 3.11
Classifier: Programming Language :: Python :: 3.12
Requires-Python: >=3.8
License-File: LICENSE
Requires-Dist: flask-cors (>=4.0.0)
Requires-Dist: flask (>=3.0.0)
Requires-Dist: psutil (>=5.9.6)
Requires-Dist: python-dotenv (>=1.0.0)
Requires-Dist: requests (>=2.31.0)
Requires-Dist: websocket-client (>=1.7.0)
Provides-Extra: dev
Requires-Dist: black (>=23.7.0) ; extra == 'dev'
Requires-Dist: build (>=0.10.0) ; extra == 'dev'
Requires-Dist: flake8 (>=6.0.0) ; extra == 'dev'
Requires-Dist: pytest-cov (>=4.1.0) ; extra == 'dev'
Requires-Dist: pytest (>=7.4.0) ; extra == 'dev'
Requires-Dist: twine (>=4.0.0) ; extra == 'dev'
Provides-Extra: windows
Requires-Dist: pywin32 (>=306) ; (sys_platform == "win32") and extra == 'windows'
